fid_score/__init__.py
fid_score/fid_score.py
fid_score/inception.py
fid_score-0.1.3.dist-info/METADATA
fid_score-0.1.3.dist-info/WHEEL
fid_score-0.1.3.dist-info/dependency_links.txt
fid_score-0.1.3.dist-info/top_level.txt
fid_score-0.1.3.dist-info/RECORD
