Metadata-Version: 2.1
Name: fid-score
Version: 0.1.3
Summary: It calculates the FID score between source and target images
Home-page: UNKNOWN
Author: Rayyan Akhtar
Author-email: akhtar.rayyan@live.com
License: MIT
Platform: UNKNOWN
Classifier: Programming Language :: Python :: 3
Classifier: Programming Language :: Python :: 3.6
Classifier: Programming Language :: Python :: 3.7
Requires-Dist: scipy (==1.3.2)
Requires-Dist: pillow (>=7.0.0)
Requires-Dist: numpy (>=1.18.1)
